{
"stock_code": "A000150",
"stock_name": "두산",
"stock_Div": "복합기업",
"stock_Div_PER": "24.59",
"Current_PER": "10.86",
"Current_PER_Rank": "1",
"Close_Price": "53300",
"PER_Target_1": "-102389",
"PER_Target_2": "-103585",
"PER_Target_Avr": "-102987",
"Price_over_PERAvg": "-0.517541048870246",
"stock_Div_PBR": "0.84",
"Current_PBR": "0.57",
"Current_PBR_Rank": "2",
"PBR_Target_1": "59963",
"PBR_Target_2": "60263",
"PBR_Target_Avr": "60113",
"Price_over_PBRAvg": "0.886663450501555",
"SRIM_1": "48344",
"SRIM_2": "42868",
"SRIM_3": "32769",
"SRIM_2R": "1.2433537930512",
"P_3": "909",
"P_2": "79",
"P_1": "2174",
"P_E": "",
"PY_3": "11676",
"PY_2": "11764",
"PY_1": "12619",
"PY_E": "8802",
"MY_3": "169134",
"MY_2": "174493",
"MY_1": "185357",
"MY_E": "177013",
"JY_3": "24741",
"JY_2": "20115",
"JY_1": "15625",
"JY_E": "14240",
"ROE_3": "1.67",
"ROE_2": "-5.21",
"ROE_1": "23.52",
"ROE_E": "-6.28",
"Total_P": "8807",
"Total_Q": "18412469",
"BETA": "1.45",
"SY_R": "0.7",
"D_R": "0.0976"
}
