{
"stock_code": "A000890",
"stock_name": "보해양조",
"stock_Div": "음료",
"stock_Div_PER": "94.88",
"Current_PER": "N/A",
"Current_PER_Rank": "N/A",
"Close_Price": "988",
"PER_Target_1": "-10456",
"PER_Target_2": "-1734",
"PER_Target_Avr": "-6095",
"Price_over_PERAvg": "-0.162100082034454",
"stock_Div_PBR": "1.79",
"Current_PBR": "1.54",
"Current_PBR_Rank": "8",
"PBR_Target_1": "1080",
"PBR_Target_2": "1097",
"PBR_Target_Avr": "1088",
"Price_over_PBRAvg": "0.90767110702802",
"SRIM_1": "373",
"SRIM_2": "174",
"SRIM_3": "27",
"SRIM_2R": "5.6695932552244",
"P_3": "-2",
"P_2": "8",
"P_1": "6",
"P_E": "",
"PY_3": "21",
"PY_2": "-110",
"PY_1": "-111",
"PY_E": "",
"MY_3": "996",
"MY_2": "820",
"MY_1": "760",
"MY_E": "",
"JY_3": "996",
"JY_2": "694",
"JY_1": "800",
"JY_E": "",
"ROE_3": "11.48",
"ROE_2": "-32.98",
"ROE_1": "-19.66",
"ROE_E": "",
"Total_P": "1259",
"Total_Q": "127430346",
"BETA": "1.02",
"SY_R": "-11.34",
"D_R": "-"
}
