{
"stock_code": "A001740",
"stock_name": "SK네트웍스",
"stock_Div": "복합기업",
"stock_Div_PER": "25.59",
"Current_PER": "N/A",
"Current_PER_Rank": "N/A",
"Close_Price": "4520",
"PER_Target_1": "11864",
"PER_Target_2": "40016",
"PER_Target_Avr": "25940",
"Price_over_PERAvg": "0.174248265227448",
"stock_Div_PBR": "0.8",
"Current_PBR": "0.47",
"Current_PBR_Rank": "1",
"PBR_Target_1": "6895",
"PBR_Target_2": "5698",
"PBR_Target_Avr": "6296",
"Price_over_PBRAvg": "",
"SRIM_1": "8937",
"SRIM_2": "8528",
"SRIM_3": "7687",
"SRIM_2R": "0.530049442984301",
"P_3": "-548",
"P_2": "409",
"P_1": "303",
"P_E": "498",
"PY_3": "1428",
"PY_2": "1335",
"PY_1": "1094",
"PY_E": "1679",
"MY_3": "152023",
"MY_2": "126458",
"MY_1": "130542",
"MY_E": "111515",
"JY_3": "23702",
"JY_2": "23366",
"JY_1": "21634",
"JY_E": "21984",
"ROE_3": "1.39",
"ROE_2": "0.31",
"ROE_1": "-5.85",
"ROE_E": "5.56",
"Total_P": "11218",
"Total_Q": "218668329",
"BETA": "0.92",
"SY_R": "10.25",
"D_R": "0.0265"
}
