{
"stock_code": "A001470",
"stock_name": "삼부토건",
"stock_Div": "건설",
"stock_Div_PER": "6.52",
"Current_PER": "25.7",
"Current_PER_Rank": "42",
"Close_Price": "902",
"PER_Target_1": "359",
"PER_Target_2": "362",
"PER_Target_Avr": "360",
"Price_over_PERAvg": "2.50208044382802",
"stock_Div_PBR": "0.88",
"Current_PBR": "0.6",
"Current_PBR_Rank": "28",
"PBR_Target_1": "1281",
"PBR_Target_2": "689",
"PBR_Target_Avr": "985",
"Price_over_PBRAvg": "",
"SRIM_1": "1311",
"SRIM_2": "1020",
"SRIM_3": "575",
"SRIM_2R": "0.884726357308675",
"P_3": "19",
"P_2": "7",
"P_1": "22",
"P_E": "",
"PY_3": "-194",
"PY_2": "-94",
"PY_1": "50",
"PY_E": "",
"MY_3": "2804",
"MY_2": "1774",
"MY_1": "2263",
"MY_E": "",
"JY_3": "2361",
"JY_2": "1972",
"JY_1": "2084",
"JY_E": "",
"ROE_3": "-14.52",
"ROE_2": "-23.52",
"ROE_1": "3.66",
"ROE_E": "",
"Total_P": "1241",
"Total_Q": "137546368",
"BETA": "1.12",
"SY_R": "24.82",
"D_R": "-"
}
