{
"stock_code": "A003030",
"stock_name": "세아제강지주",
"stock_Div": "철강",
"stock_Div_PER": "43.72",
"Current_PER": "N/A",
"Current_PER_Rank": "N/A",
"Close_Price": "46350",
"PER_Target_1": "-30818",
"PER_Target_2": "-6192",
"PER_Target_Avr": "-18505",
"Price_over_PERAvg": "-2.50472845176979",
"stock_Div_PBR": "0.63",
"Current_PBR": "0.19",
"Current_PBR_Rank": "3",
"PBR_Target_1": "139646",
"PBR_Target_2": "66732",
"PBR_Target_Avr": "103189",
"Price_over_PBRAvg": "0.449175784240568",
"SRIM_1": "249148",
"SRIM_2": "239819",
"SRIM_3": "220414",
"SRIM_2R": "0.193270891831835",
"P_3": "-56",
"P_2": "287",
"P_1": "129",
"P_E": "",
"PY_3": "522",
"PY_2": "805",
"PY_1": "631",
"PY_E": "",
"MY_3": "15070",
"MY_2": "17817",
"MY_1": "26439",
"MY_E": "",
"JY_3": "12370",
"JY_2": "9413",
"JY_1": "9649",
"JY_E": "",
"ROE_3": "2.04",
"ROE_2": "29.05",
"ROE_1": "-0.32",
"ROE_E": "",
"Total_P": "1920",
"Total_Q": "4040461",
"BETA": "0.95",
"SY_R": "3.04",
"D_R": "0.0324"
}
