{
"stock_code": "A003300",
"stock_name": "한일홀딩스",
"stock_Div": "건축자재",
"stock_Div_PER": "40.17",
"Current_PER": "19.37",
"Current_PER_Rank": "11",
"Close_Price": "47250",
"PER_Target_1": "87924",
"PER_Target_2": "20570",
"PER_Target_Avr": "54247",
"Price_over_PERAvg": "0.871015908713846",
"stock_Div_PBR": "1.12",
"Current_PBR": "0.25",
"Current_PBR_Rank": "2",
"PBR_Target_1": "177673",
"PBR_Target_2": "52768",
"PBR_Target_Avr": "115220",
"Price_over_PBRAvg": "",
"SRIM_1": "196813",
"SRIM_2": "213306",
"SRIM_3": "254161",
"SRIM_2R": "0.221512527956412",
"P_3": "179",
"P_2": "-8",
"P_1": "555",
"P_E": "",
"PY_3": "1126",
"PY_2": "411",
"PY_1": "836",
"PY_E": "",
"MY_3": "11908",
"MY_2": "11867",
"MY_1": "16518",
"MY_E": "",
"JY_3": "15337",
"JY_2": "10002",
"JY_1": "10010",
"JY_E": "",
"ROE_3": "3.79",
"ROE_2": "40.39",
"ROE_1": "1.38",
"ROE_E": "",
"Total_P": "2832",
"Total_Q": "5763156",
"BETA": "0.5",
"SY_R": "3.39",
"D_R": "0.0487"
}
