{
"stock_code": "A003220",
"stock_name": "대원제약",
"stock_Div": "제약",
"stock_Div_PER": "135.81",
"Current_PER": "15.16",
"Current_PER_Rank": "15",
"Close_Price": "21650",
"PER_Target_1": "185143",
"PER_Target_2": "27535",
"PER_Target_Avr": "106339",
"Price_over_PERAvg": "0.203594165828153",
"SRIM_1": "12868",
"SRIM_2": "14308",
"SRIM_3": "18013",
"SRIM_2R": "1.51315797400351",
"P_3": "84",
"P_2": "104",
"P_1": "101",
"P_E": "83",
"PY_3": "253",
"PY_2": "307",
"PY_1": "351",
"PY_E": "387",
"MY_3": "2655",
"MY_2": "2867",
"MY_1": "3178",
"MY_E": "3399",
"JY_3": "1680",
"JY_2": "1835",
"JY_1": "2049",
"JY_E": "2252",
"ROE_3": "6.52",
"ROE_2": "13.51",
"ROE_1": "14.05",
"ROE_E": "13.51",
"Total_P": "4383",
"Total_Q": "19626877",
"BETA": "0.79",
"SY_R": "12.49",
"D_R": "0.0117"
}
