{
"stock_code": "A004690",
"stock_name": "삼천리",
"stock_Div": "가스유틸리티",
"stock_Div_PER": "27.83",
"Current_PER": "22.98",
"Current_PER_Rank": "11",
"Close_Price": "76500",
"PER_Target_1": "201461",
"PER_Target_2": "119421",
"PER_Target_Avr": "160441",
"Price_over_PERAvg": "0.476810790259348",
"stock_Div_PBR": "0.41",
"Current_PBR": "0.2",
"Current_PBR_Rank": "1",
"PBR_Target_1": "129235",
"PBR_Target_2": "102857",
"PBR_Target_Avr": "116046",
"Price_over_PBRAvg": "",
"SRIM_1": "309442",
"SRIM_2": "276649",
"SRIM_3": "215445",
"SRIM_2R": "0.276524067094722",
"P_3": "72",
"P_2": "645",
"P_1": "23",
"P_E": "54",
"PY_3": "611",
"PY_2": "839",
"PY_1": "856",
"PY_E": "808",
"MY_3": "32951",
"MY_2": "34562",
"MY_1": "34616",
"MY_E": "34704",
"JY_3": "12396",
"JY_2": "12577",
"JY_1": "12843",
"JY_E": "12952",
"ROE_3": "1.07",
"ROE_2": "2.57",
"ROE_1": "2.98",
"ROE_E": "2.4",
"Total_P": "3102",
"Total_Q": "3424025",
"BETA": "0.5",
"SY_R": "3.62",
"D_R": "0.0392"
}
