{
"stock_code": "A004150",
"stock_name": "한솔홀딩스",
"stock_Div": "종이와목재",
"stock_Div_PER": "20.48",
"Current_PER": "3.35",
"Current_PER_Rank": "1",
"Close_Price": "3330",
"PER_Target_1": "16888",
"PER_Target_2": "6779",
"PER_Target_Avr": "11834",
"Price_over_PERAvg": "0.281404487260743",
"stock_Div_PBR": "2.38",
"Current_PBR": "0.3",
"Current_PBR_Rank": "5",
"PBR_Target_1": "27496",
"PBR_Target_2": "6299",
"PBR_Target_Avr": "16898",
"Price_over_PBRAvg": "0.197070572569907",
"SRIM_1": "10490",
"SRIM_2": "10097",
"SRIM_3": "9279",
"SRIM_2R": "0.329810822523006",
"P_3": "-32",
"P_2": "23",
"P_1": "37",
"P_E": "",
"PY_3": "256",
"PY_2": "254",
"PY_1": "118",
"PY_E": "120",
"MY_3": "6868",
"MY_2": "6020",
"MY_1": "5416",
"MY_E": "5130",
"JY_3": "4670",
"JY_2": "4090",
"JY_1": "4339",
"JY_E": "4750",
"ROE_3": "-11.11",
"ROE_2": "-8.9",
"ROE_1": "6",
"ROE_E": "8.36",
"Total_P": "1399",
"Total_Q": "42008577",
"BETA": "0.89",
"SY_R": "11.86",
"D_R": "-"
}
