{
"stock_code": "A007570",
"stock_name": "일양약품",
"stock_Div": "제약",
"stock_Div_PER": "99.35",
"Current_PER": "163.06",
"Current_PER_Rank": "73",
"Close_Price": "79200",
"PER_Target_1": "48229",
"PER_Target_2": "72419",
"PER_Target_Avr": "60324",
"Price_over_PERAvg": "1.31291028446389",
"stock_Div_PBR": "4.94",
"Current_PBR": "7.32",
"Current_PBR_Rank": "107",
"PBR_Target_1": "49042",
"PBR_Target_2": "36554",
"PBR_Target_Avr": "42798",
"Price_over_PBRAvg": "",
"SRIM_1": "10919",
"SRIM_2": "10526",
"SRIM_3": "9708",
"SRIM_2R": "7.52401489312713",
"P_3": "61",
"P_2": "68",
"P_1": "75",
"P_E": "",
"PY_3": "244",
"PY_2": "167",
"PY_1": "325",
"PY_E": "",
"MY_3": "2698",
"MY_2": "3000",
"MY_1": "3246",
"MY_E": "",
"JY_3": "1919",
"JY_2": "1875",
"JY_1": "1969",
"JY_E": "",
"ROE_3": "3.28",
"ROE_2": "-2.58",
"ROE_1": "5.2",
"ROE_E": "",
"Total_P": "15116",
"Total_Q": "18650260",
"BETA": "0.86",
"SY_R": "46.51",
"D_R": "0.0015"
}
