{
"stock_code": "A009410",
"stock_name": "태영건설",
"stock_Div": "건설",
"stock_Div_PER": "8.05",
"Current_PER": "1.54",
"Current_PER_Rank": "3",
"Close_Price": "13000",
"PER_Target_1": "64484",
"PER_Target_2": "2405987",
"PER_Target_Avr": "1235236",
"Price_over_PERAvg": "0.010524308927326",
"stock_Div_PBR": "1.27",
"Current_PBR": "0.81",
"Current_PBR_Rank": "18",
"PBR_Target_1": "19275",
"PBR_Target_2": "7125",
"PBR_Target_Avr": "13200",
"Price_over_PBRAvg": "0.984848484848485",
"SRIM_1": "27066",
"SRIM_2": "50051",
"SRIM_3": "175427",
"SRIM_2R": "0.259735395806773",
"P_3": "778",
"P_2": "897",
"P_1": "-243",
"P_E": "",
"PY_3": "4582",
"PY_2": "2764",
"PY_1": "2509",
"PY_E": "",
"MY_3": "36911",
"MY_2": "29671",
"MY_1": "22815",
"MY_E": "",
"JY_3": "10144",
"JY_2": "11552",
"JY_1": "6422",
"JY_E": "",
"ROE_3": "19.21",
"ROE_2": "8.38",
"ROE_1": "61.96",
"ROE_E": "",
"Total_P": "5057",
"Total_Q": "40193460",
"BETA": "0.72",
"SY_R": "2.02",
"D_R": "0.025"
}
