{
"stock_code": "A011210",
"stock_name": "현대위아",
"stock_Div": "자동차부품",
"stock_Div_PER": "27.95",
"Current_PER": "18.01",
"Current_PER_Rank": "38",
"Close_Price": "41750",
"PER_Target_1": "67629",
"PER_Target_2": "41805",
"PER_Target_Avr": "54717",
"Price_over_PERAvg": "0.763016978270007",
"stock_Div_PBR": "1.12",
"Current_PBR": "0.36",
"Current_PBR_Rank": "28",
"PBR_Target_1": "127363",
"PBR_Target_2": "67033",
"PBR_Target_Avr": "97198",
"Price_over_PBRAvg": "0.429535587151999",
"SRIM_1": "102387",
"SRIM_2": "94486",
"SRIM_3": "79040",
"SRIM_2R": "0.441863907841125",
"P_3": "202",
"P_2": "845",
"P_1": "-386",
"P_E": "132",
"PY_3": "167",
"PY_2": "50",
"PY_1": "1019",
"PY_E": "1055",
"MY_3": "74874",
"MY_2": "78805",
"MY_1": "73146",
"MY_E": "63296",
"JY_3": "31401",
"JY_2": "30369",
"JY_1": "30918",
"JY_E": "31421",
"ROE_3": "-1.97",
"ROE_2": "-1.8",
"ROE_1": "1.8",
"ROE_E": "2.22",
"Total_P": "11354",
"Total_Q": "26561729",
"BETA": "1.71",
"SY_R": "11.14",
"D_R": "0.0168"
}
