{
"stock_code": "A012030",
"stock_name": "DB",
"stock_Div": "IT¼­ºñ½º",
"stock_Div_PER": "28.8",
"Current_PER": "20.61",
"Current_PER_Rank": "21",
"Close_Price": "963",
"PER_Target_1": "848",
"PER_Target_2": "1019",
"PER_Target_Avr": "934",
"Price_over_PERAvg": "1.03160149973219",
"stock_Div_PBR": "2.63",
"Current_PBR": "0.53",
"Current_PBR_Rank": "2",
"PBR_Target_1": "4250",
"PBR_Target_2": "1259",
"PBR_Target_Avr": "2754",
"Price_over_PBRAvg": "0.349609729533491",
"SRIM_1": "1554",
"SRIM_2": "1384",
"SRIM_3": "1069",
"SRIM_2R": "0.695887475237729",
"P_3": "42",
"P_2": "64",
"P_1": "103",
"P_E": "",
"PY_3": "16",
"PY_2": "185",
"PY_1": "269",
"PY_E": "",
"MY_3": "2371",
"MY_2": "2385",
"MY_1": "2724",
"MY_E": "",
"JY_3": "1376",
"JY_2": "2110",
"JY_1": "3137",
"JY_E": "",
"ROE_3": "-2.87",
"ROE_2": "2.53",
"ROE_1": "2.39",
"ROE_E": "",
"Total_P": "1937",
"Total_Q": "191030533",
"BETA": "0.69",
"SY_R": "7.2",
"D_R": "-"
}
