{
"stock_code": "A012860",
"stock_name": "모베이스전자",
"stock_Div": "자동차부품",
"stock_Div_PER": "14.18",
"Current_PER": "N/A",
"Current_PER_Rank": "N/A",
"Close_Price": "1260",
"PER_Target_1": "-5348",
"PER_Target_2": "-2066",
"PER_Target_Avr": "-3707",
"Price_over_PERAvg": "-0.339897491232803",
"stock_Div_PBR": "0.99",
"Current_PBR": "0.44",
"Current_PBR_Rank": "52",
"PBR_Target_1": "4876",
"PBR_Target_2": "2094",
"PBR_Target_Avr": "3485",
"Price_over_PBRAvg": "",
"SRIM_1": "2203",
"SRIM_2": "1426",
"SRIM_3": "518",
"SRIM_2R": "0.883424169161294",
"P_3": "12",
"P_2": "80",
"P_1": "-18",
"P_E": "",
"PY_3": "-143",
"PY_2": "17",
"PY_1": "109",
"PY_E": "",
"MY_3": "7102",
"MY_2": "7180",
"MY_1": "7717",
"MY_E": "",
"JY_3": "1266",
"JY_2": "1227",
"JY_1": "1527",
"JY_E": "",
"ROE_3": "-27.13",
"ROE_2": "-10.9",
"ROE_1": "-8.51",
"ROE_E": "",
"Total_P": "655",
"Total_Q": "51800800",
"BETA": "1.19",
"SY_R": "6.01",
"D_R": "-"
}
