{
"stock_code": "A027360",
"stock_name": "아주IB투자",
"stock_Div": "창업투자",
"stock_Div_PER": "25.22",
"Current_PER": "19.7",
"Current_PER_Rank": "7",
"Close_Price": "1395",
"PER_Target_1": "3282",
"PER_Target_2": "1323",
"PER_Target_Avr": "2302",
"Price_over_PERAvg": "0.60586319218241",
"stock_Div_PBR": "1.6",
"Current_PBR": "1.01",
"Current_PBR_Rank": "3",
"PBR_Target_1": "2168",
"PBR_Target_2": "1219",
"PBR_Target_Avr": "1694",
"Price_over_PBRAvg": "0.823737821080602",
"SRIM_1": "1499",
"SRIM_2": "1451",
"SRIM_3": "1351",
"SRIM_2R": "0.96120819497543",
"P_3": "-17",
"P_2": "111",
"P_1": "-19",
"P_E": "",
"PY_3": "163",
"PY_2": "149",
"PY_1": "217",
"PY_E": "",
"MY_3": "263",
"MY_2": "253",
"MY_1": "332",
"MY_E": "",
"JY_3": "1313",
"JY_2": "1559",
"JY_1": "1676",
"JY_E": "",
"ROE_3": "",
"ROE_2": "8.19",
"ROE_1": "10.07",
"ROE_E": "",
"Total_P": "1656",
"Total_Q": "114903273",
"BETA": "1.09",
"SY_R": "7.63",
"D_R": "0.0251"
}
