{
"stock_code": "A034300",
"stock_name": "신세계건설",
"stock_Div": "건설",
"stock_Div_PER": "6.21",
"Current_PER": "4.32",
"Current_PER_Rank": "10",
"Close_Price": "21250",
"PER_Target_1": "25834",
"PER_Target_2": "23673",
"PER_Target_Avr": "24754",
"Price_over_PERAvg": "0.858464459571374",
"stock_Div_PBR": "0.86",
"Current_PBR": "0.43",
"Current_PBR_Rank": "9",
"PBR_Target_1": "40356",
"PBR_Target_2": "48111",
"PBR_Target_Avr": "44234",
"Price_over_PBRAvg": "",
"SRIM_1": "57481",
"SRIM_2": "64205",
"SRIM_3": "81620",
"SRIM_2R": "0.330969638041281",
"P_3": "0",
"P_2": "",
"P_1": "",
"P_E": "",
"PY_3": "247",
"PY_2": "218",
"PY_1": "242",
"PY_E": "",
"MY_3": "10644",
"MY_2": "10843",
"MY_1": "10162",
"MY_E": "",
"JY_3": "1597",
"JY_2": "1956",
"JY_1": "1976",
"JY_E": "",
"ROE_3": "20.18",
"ROE_2": "24.25",
"ROE_1": "8.91",
"ROE_E": "",
"Total_P": "850",
"Total_Q": "4000000",
"BETA": "0.74",
"SY_R": "3.51",
"D_R": "0.0376"
}
