{
"stock_code": "A035600",
"stock_name": "KG이니시스",
"stock_Div": "IT서비스",
"stock_Div_PER": "23.79",
"Current_PER": "12.14",
"Current_PER_Rank": "10",
"Close_Price": "19850",
"PER_Target_1": "40500",
"PER_Target_2": "36694",
"PER_Target_Avr": "38597",
"Price_over_PERAvg": "0.514288675285644",
"stock_Div_PBR": "2.37",
"Current_PBR": "1.85",
"Current_PBR_Rank": "32",
"PBR_Target_1": "21626",
"PBR_Target_2": "20497",
"PBR_Target_Avr": "21062",
"Price_over_PBRAvg": "0.94247798115044",
"SRIM_1": "12800",
"SRIM_2": "17221",
"SRIM_3": "32297",
"SRIM_2R": "1.15265054344974",
"P_3": "238",
"P_2": "228",
"P_1": "250",
"P_E": "268",
"PY_3": "547",
"PY_2": "604",
"PY_1": "861",
"PY_E": "",
"MY_3": "7585",
"MY_2": "9246",
"MY_1": "9561",
"MY_E": "",
"JY_3": "1869",
"JY_2": "2133",
"JY_1": "2494",
"JY_E": "",
"ROE_3": "-0.21",
"ROE_2": "17.61",
"ROE_1": "21.61",
"ROE_E": "",
"Total_P": "5553",
"Total_Q": "26618488",
"BETA": "0.96",
"SY_R": "6.45",
"D_R": "0.0166"
}
