{
"stock_code": "A042660",
"stock_name": "대우조선해양",
"stock_Div": "조선",
"stock_Div_PER": "N/A",
"Current_PER": "2925.37",
"Current_PER_Rank": "11",
"Close_Price": "23400",
"PER_Target_1": "0",
"PER_Target_2": "21068",
"PER_Target_Avr": "10534",
"Price_over_PERAvg": "1.11068919688627",
"SRIM_1": "33888",
"SRIM_2": "32229",
"SRIM_3": "28839",
"SRIM_2R": "0.726059591923706",
"P_3": "-2563",
"P_2": "1546",
"P_1": "2790",
"P_E": "805",
"PY_3": "7330",
"PY_2": "10248",
"PY_1": "2928",
"PY_E": "4642",
"Total_P": "25086",
"D_R": "-"
}
