{
"stock_code": "A052260",
"stock_name": "현대바이오랜드",
"stock_Div": "화장품",
"stock_Div_PER": "84.21",
"Current_PER": "66.3",
"Current_PER_Rank": "13",
"Close_Price": "24400",
"PER_Target_1": "57840",
"PER_Target_2": "18825",
"PER_Target_Avr": "38332",
"Price_over_PERAvg": "0.636535576860367",
"stock_Div_PBR": "8.49",
"Current_PBR": "2.38",
"Current_PBR_Rank": "30",
"PBR_Target_1": "83736",
"PBR_Target_2": "23422",
"PBR_Target_Avr": "53579",
"Price_over_PBRAvg": "0.455402303141156",
"SRIM_1": "10805",
"SRIM_2": "10274",
"SRIM_3": "9190",
"SRIM_2R": "2.37487265704164",
"P_3": "13",
"P_2": "27",
"P_1": "-4",
"P_E": "",
"PY_3": "160",
"PY_2": "171",
"PY_1": "145",
"PY_E": "",
"MY_3": "1026",
"MY_2": "1006",
"MY_1": "1063",
"MY_E": "",
"JY_3": "1378",
"JY_2": "1489",
"JY_1": "1557",
"JY_E": "",
"ROE_3": "8.93",
"ROE_2": "10.5",
"ROE_1": "7.12",
"ROE_E": "",
"Total_P": "3660",
"Total_Q": "15000000",
"BETA": "0.9",
"SY_R": "25.24",
"D_R": "0.0143"
}
