{
"stock_code": "A058220",
"stock_name": "아리온",
"stock_Div": "전자제품",
"stock_Div_PER": "15.26",
"Current_PER": "N/A",
"Current_PER_Rank": "N/A",
"Close_Price": "275",
"PER_Target_1": "-328430",
"PER_Target_2": "-1995",
"PER_Target_Avr": "-165212",
"Price_over_PERAvg": "-1.66452296285087E-03",
"stock_Div_PBR": "1.6",
"Current_PBR": "N/A",
"Current_PBR_Rank": "18",
"PBR_Target_1": "-10566",
"PBR_Target_2": "-782",
"PBR_Target_Avr": "-5674",
"Price_over_PBRAvg": "-0.048466690165668",
"SRIM_1": "583",
"SRIM_2": "-39",
"SRIM_3": "-6202478",
"SRIM_2R": "-7.0220107110528",
"P_3": "-36",
"P_2": "-44",
"P_1": "8",
"P_E": "",
"PY_3": "-59",
"PY_2": "21",
"PY_1": "-109",
"PY_E": "",
"MY_3": "459",
"MY_2": "330",
"MY_1": "82",
"MY_E": "",
"JY_3": "250",
"JY_2": "190",
"JY_1": "-90",
"JY_E": "",
"ROE_3": "-47.35",
"ROE_2": "-34.27",
"ROE_1": "-586.75",
"ROE_E": "",
"Total_P": "107",
"Total_Q": "1297652",
"BETA": "0",
"SY_R": "-0.98",
"D_R": "-"
}
