{
"stock_code": "A060560",
"stock_name": "홈센타홀딩스",
"stock_Div": "건축자재",
"stock_Div_PER": "N/A",
"Current_PER": "115.68",
"Current_PER_Rank": "21",
"Close_Price": "1375",
"PER_Target_1": "0",
"PER_Target_2": "-294",
"PER_Target_Avr": "-147",
"Price_over_PERAvg": "",
"stock_Div_PBR": "1.07",
"Current_PBR": "1.45",
"Current_PBR_Rank": "25",
"PBR_Target_1": "980",
"PBR_Target_2": "1118",
"PBR_Target_Avr": "1049",
"Price_over_PBRAvg": "",
"SRIM_1": "912",
"SRIM_2": "816",
"SRIM_3": "637",
"SRIM_2R": "",
"P_3": "33",
"P_2": "-8",
"P_1": "31",
"P_E": "",
"PY_3": "15",
"PY_2": "-49",
"PY_1": "26",
"PY_E": "",
"MY_3": "2344",
"MY_2": "2390",
"MY_1": "2656",
"MY_E": "",
"JY_3": "1050",
"JY_2": "808",
"JY_1": "795",
"JY_E": "",
"ROE_3": "-45.91",
"ROE_2": "-38.92",
"ROE_1": "-2.44",
"ROE_E": "",
"Total_P": "1170",
"Total_Q": "84383500",
"BETA": "0.58",
"SY_R": "45",
"D_R": "-"
}
