{
"stock_code": "A065690",
"stock_name": "파커스",
"stock_Div": "컴퓨터와주변기기",
"stock_Div_PER": "N/A",
"Current_PER": "N/A",
"Current_PER_Rank": "N/A",
"Close_Price": "3000",
"PER_Target_1": "0",
"PER_Target_2": "-8824",
"PER_Target_Avr": "-4412",
"Price_over_PERAvg": "-0.339981867633726",
"stock_Div_PBR": "2.06",
"Current_PBR": "0.54",
"Current_PBR_Rank": "1",
"PBR_Target_1": "10983",
"PBR_Target_2": "2795",
"PBR_Target_Avr": "6889",
"Price_over_PBRAvg": "0.435476847147627",
"SRIM_1": "3934",
"SRIM_2": "2457",
"SRIM_3": "816",
"SRIM_2R": "1.22080676609043",
"P_3": "1",
"P_2": "6",
"P_1": "-15",
"P_E": "",
"PY_3": "22",
"PY_2": "-41",
"PY_1": "-22",
"PY_E": "",
"MY_3": "1002",
"MY_2": "1008",
"MY_1": "783",
"MY_E": "",
"JY_3": "932",
"JY_2": "826",
"JY_1": "738",
"JY_E": "",
"ROE_3": "4.99",
"ROE_2": "-4.06",
"ROE_1": "-10.56",
"ROE_E": "",
"Total_P": "419",
"Total_Q": "13244875",
"BETA": "0.8",
"SY_R": "-19.05",
"D_R": "0.05"
}
