{
"stock_code": "A068290",
"stock_name": "삼성출판사",
"stock_Div": "문구류",
"stock_Div_PER": "5.41",
"Current_PER": "90.82",
"Current_PER_Rank": "2",
"Close_Price": "32750",
"PER_Target_1": "2503",
"PER_Target_2": "47274",
"PER_Target_Avr": "24888",
"Price_over_PERAvg": "1.31586877473532",
"stock_Div_PBR": "1.98",
"Current_PBR": "3.53",
"Current_PBR_Rank": "3",
"PBR_Target_1": "17059",
"PBR_Target_2": "15562",
"PBR_Target_Avr": "16310",
"Price_over_PBRAvg": "2.00790901566476",
"SRIM_1": "9398",
"SRIM_2": "8745",
"SRIM_3": "7453",
"SRIM_2R": "3.74492348766526",
"P_3": "7",
"P_2": "-18",
"P_1": "-22",
"P_E": "",
"PY_3": "110",
"PY_2": "33",
"PY_1": "48",
"PY_E": "",
"MY_3": "1766",
"MY_2": "1861",
"MY_1": "2020",
"MY_E": "",
"JY_3": "877",
"JY_2": "869",
"JY_1": "907",
"JY_E": "",
"ROE_3": "3.92",
"ROE_2": "0.38",
"ROE_1": "5.49",
"ROE_E": "",
"Total_P": "3275",
"Total_Q": "10000000",
"BETA": "1.2",
"SY_R": "68.23",
"D_R": "0.0031"
}
