{
"stock_code": "A074610",
"stock_name": "이엔플러스",
"stock_Div": "기계",
"stock_Div_PER": "N/A",
"Current_PER": "N/A",
"Current_PER_Rank": "N/A",
"Close_Price": "3705",
"PER_Target_1": "0",
"PER_Target_2": "-7090",
"PER_Target_Avr": "-3545",
"Price_over_PERAvg": "-0.522566995768688",
"stock_Div_PBR": "2.1",
"Current_PBR": "2.82",
"Current_PBR_Rank": "80",
"PBR_Target_1": "2617",
"PBR_Target_2": "6870",
"PBR_Target_Avr": "4744",
"Price_over_PBRAvg": "0.781068831031938",
"SRIM_1": "346",
"SRIM_2": "70",
"SRIM_3": "1",
"SRIM_2R": "53.3055122214657",
"P_3": "6",
"P_2": "-20",
"P_1": "-52",
"P_E": "",
"PY_3": "-113",
"PY_2": "-154",
"PY_1": "-83",
"PY_E": "",
"MY_3": "398",
"MY_2": "404",
"MY_1": "274",
"MY_E": "",
"JY_3": "325",
"JY_2": "458",
"JY_1": "555",
"JY_E": "",
"ROE_3": "-29.34",
"ROE_2": "-87.65",
"ROE_1": "-27.8",
"ROE_E": "",
"Total_P": "1739",
"Total_Q": "47340159",
"BETA": "0.82",
"SY_R": "-20.95",
"D_R": "-"
}
