{
"stock_code": "A085660",
"stock_name": "차바이오텍",
"stock_Div": "생물공학",
"stock_Div_PER": "N/A",
"Current_PER": "23.98",
"Current_PER_Rank": "5",
"Close_Price": "22450",
"PER_Target_1": "0",
"PER_Target_2": "0",
"PER_Target_Avr": "0",
"Price_over_PERAvg": "N/A",
"SRIM_1": "8267",
"SRIM_2": "9238",
"SRIM_3": "11755",
"SRIM_2R": "2.43006793400793",
"P_3": "-83",
"P_2": "94",
"P_1": "-30",
"P_E": "",
"PY_3": "-67",
"PY_2": "190",
"PY_1": "58",
"PY_E": "",
"MY_3": "4175",
"MY_2": "4886",
"MY_1": "5346",
"MY_E": "",
"JY_3": "2307",
"JY_2": "3270",
"JY_1": "3772",
"JY_E": "",
"ROE_3": "-18.74",
"ROE_2": "8.75",
"ROE_1": "13.17",
"ROE_E": "",
"Total_P": "11785",
"Total_Q": "52495450",
"BETA": "0.95",
"SY_R": "203.19",
"D_R": "-"
}
