{
"stock_code": "A086900",
"stock_name": "메디톡스",
"stock_Div": "생물공학",
"stock_Div_PER": "N/A",
"Current_PER": "N/A",
"Current_PER_Rank": "N/A",
"Close_Price": "219100",
"PER_Target_1": "0",
"PER_Target_2": "-67749",
"PER_Target_Avr": "-33874",
"Price_over_PERAvg": "-3.23399607374279",
"stock_Div_PBR": "12.99",
"Current_PBR": "5.05",
"Current_PBR_Rank": "14",
"PBR_Target_1": "924020",
"PBR_Target_2": "837574",
"PBR_Target_Avr": "880797",
"Price_over_PBRAvg": "0.248751982579414",
"SRIM_1": "74869",
"SRIM_2": "80222",
"SRIM_3": "93261",
"SRIM_2R": "2.73117519833679",
"P_3": "-99",
"P_2": "-41",
"P_1": "-114",
"P_E": "26",
"PY_3": "870",
"PY_2": "855",
"PY_1": "257",
"PY_E": "-229",
"MY_3": "1812",
"MY_2": "2054",
"MY_1": "2059",
"MY_E": "1558",
"JY_3": "1917",
"JY_2": "2526",
"JY_1": "2591",
"JY_E": "3767",
"ROE_3": "41.32",
"ROE_2": "31.5",
"ROE_1": "10.24",
"ROE_E": "-2.58",
"Total_P": "13097",
"Total_Q": "5544949",
"BETA": "0.87",
"SY_R": "50.96",
"D_R": "0.0035"
}
