{
"stock_code": "A086960",
"stock_name": "한컴MDS",
"stock_Div": "소프트웨어",
"stock_Div_PER": "87.79",
"Current_PER": "332.01",
"Current_PER_Rank": "29",
"Close_Price": "16100",
"PER_Target_1": "60465",
"PER_Target_2": "13626",
"PER_Target_Avr": "37046",
"Price_over_PERAvg": "0.43460069374148",
"stock_Div_PBR": "3.94",
"Current_PBR": "1.13",
"Current_PBR_Rank": "10",
"PBR_Target_1": "55220",
"PBR_Target_2": "22513",
"PBR_Target_Avr": "38866",
"Price_over_PBRAvg": "0.414238483012363",
"SRIM_1": "13817",
"SRIM_2": "13456",
"SRIM_3": "12692",
"SRIM_2R": "1.19648748274703",
"P_3": "25",
"P_2": "4",
"P_1": "9",
"P_E": "16",
"PY_3": "112",
"PY_2": "91",
"PY_1": "44",
"PY_E": "53",
"MY_3": "1489",
"MY_2": "1382",
"MY_1": "1549",
"MY_E": "1543",
"JY_3": "995",
"JY_2": "1079",
"JY_1": "1123",
"JY_E": "1189",
"ROE_3": "8.97",
"ROE_2": "5.82",
"ROE_1": "7.38",
"ROE_E": "5.54",
"Total_P": "1421",
"Total_Q": "8229805",
"BETA": "0.9",
"SY_R": "32.3",
"D_R": "-"
}
