{
"stock_code": "A090360",
"stock_name": "로보스타",
"stock_Div": "기계",
"stock_Div_PER": "N/A",
"Current_PER": "N/A",
"Current_PER_Rank": "N/A",
"Close_Price": "11950",
"PER_Target_1": "0",
"PER_Target_2": "-7533",
"PER_Target_Avr": "-3766",
"Price_over_PERAvg": "-1.58635337846807",
"stock_Div_PBR": "1.27",
"Current_PBR": "1.24",
"Current_PBR_Rank": "68",
"PBR_Target_1": "11931",
"PBR_Target_2": "24525",
"PBR_Target_Avr": "18228",
"Price_over_PBRAvg": "",
"SRIM_1": "7753",
"SRIM_2": "5333",
"SRIM_3": "2247",
"SRIM_2R": "2.2406141831233",
"P_3": "-19",
"P_2": "-34",
"P_1": "-40",
"P_E": "",
"PY_3": "105",
"PY_2": "22",
"PY_1": "-69",
"PY_E": "",
"MY_3": "2065",
"MY_2": "1932",
"MY_1": "1772",
"MY_E": "",
"JY_3": "503",
"JY_2": "1028",
"JY_1": "964",
"JY_E": "",
"ROE_3": "16.14",
"ROE_2": "-1.48",
"ROE_1": "-4.53",
"ROE_E": "",
"Total_P": "1165",
"Total_Q": "9750000",
"BETA": "1.42",
"SY_R": "-16.88",
"D_R": "-"
}
