{
"stock_code": "A096690",
"stock_name": "에이루트",
"stock_Div": "컴퓨터와주변기기",
"stock_Div_PER": "N/A",
"Current_PER": "N/A",
"Current_PER_Rank": "N/A",
"Close_Price": "6770",
"PER_Target_1": "0",
"PER_Target_2": "10226",
"PER_Target_Avr": "5113",
"Price_over_PERAvg": "0.662037942499511",
"stock_Div_PBR": "2.66",
"Current_PBR": "0.65",
"Current_PBR_Rank": "5",
"PBR_Target_1": "34451",
"PBR_Target_2": "18350",
"PBR_Target_Avr": "26400",
"Price_over_PBRAvg": "0.256434537224674",
"SRIM_1": "6973",
"SRIM_2": "5011",
"SRIM_3": "2345",
"SRIM_2R": "1.35110162746922",
"P_3": "-2",
"P_2": "-9",
"P_1": "-12",
"P_E": "",
"PY_3": "-14",
"PY_2": "-54",
"PY_1": "-10",
"PY_E": "",
"MY_3": "367",
"MY_2": "222",
"MY_1": "313",
"MY_E": "",
"JY_3": "827",
"JY_2": "825",
"JY_1": "1054",
"JY_E": "",
"ROE_3": "-9.35",
"ROE_2": "-8.76",
"ROE_1": "2.49",
"ROE_E": "",
"Total_P": "856",
"Total_Q": "12645368",
"BETA": "0.8",
"SY_R": "-85.6",
"D_R": "-"
}
