{
"stock_code": "A097950",
"stock_name": "CJ제일제당",
"stock_Div": "항공화물운송과물류",
"stock_Div_PER": "12.56",
"Current_PER": "17.7",
"Current_PER_Rank": "8",
"Close_Price": "440000",
"PER_Target_1": "449061",
"PER_Target_2": "567686",
"PER_Target_Avr": "508374",
"Price_over_PERAvg": "0.865505381378062",
"stock_Div_PBR": "1.2",
"Current_PBR": "1.27",
"Current_PBR_Rank": "9",
"PBR_Target_1": "411579",
"PBR_Target_2": "441184",
"PBR_Target_Avr": "426382",
"Price_over_PBRAvg": "1.03193970657733",
"SRIM_1": "353064",
"SRIM_2": "345859",
"SRIM_3": "330480",
"SRIM_2R": "1.27219543491432",
"P_3": "4021",
"P_2": "2966",
"P_1": "3851",
"P_E": "3974",
"PY_3": "8327",
"PY_2": "8969",
"PY_1": "13596",
"PY_E": "15444",
"MY_3": "186701",
"MY_2": "223525",
"MY_1": "242457",
"MY_E": "256272",
"JY_3": "47828",
"JY_2": "48809",
"JY_1": "52744",
"JY_E": "58140",
"ROE_3": "21.46",
"ROE_2": "3.16",
"ROE_1": "13.5",
"ROE_E": "11.12",
"Total_P": "66238",
"Total_Q": "16024317",
"BETA": "0.6",
"SY_R": "4.87",
"D_R": "0.0091"
}
