{
"stock_code": "A121800",
"stock_name": "비덴트",
"stock_Div": "전자장비와기기",
"stock_Div_PER": "46.2",
"Current_PER": "54.71",
"Current_PER_Rank": "39",
"Close_Price": "6790",
"PER_Target_1": "-11324",
"PER_Target_2": "-1369",
"PER_Target_Avr": "-6346",
"Price_over_PERAvg": "-1.06988103679193",
"stock_Div_PBR": "2.63",
"Current_PBR": "0.88",
"Current_PBR_Rank": "19",
"PBR_Target_1": "18309",
"PBR_Target_2": "22101",
"PBR_Target_Avr": "20205",
"Price_over_PBRAvg": "",
"SRIM_1": "6748",
"SRIM_2": "5813",
"SRIM_3": "4160",
"SRIM_2R": "1.16813382472735",
"P_3": "-11",
"P_2": "-12",
"P_1": "-8",
"P_E": "",
"PY_3": "-64",
"PY_2": "12",
"PY_1": "-18",
"PY_E": "",
"MY_3": "239",
"MY_2": "215",
"MY_1": "187",
"MY_E": "",
"JY_3": "1399",
"JY_2": "2423",
"JY_1": "2491",
"JY_E": "",
"ROE_3": "68.9",
"ROE_2": "33.48",
"ROE_1": "-3.01",
"ROE_E": "",
"Total_P": "2355",
"Total_Q": "35065706",
"BETA": "1.14",
"SY_R": "-130.83",
"D_R": "-"
}
