{
"stock_code": "A130500",
"stock_name": "GH신소재",
"stock_Div": "자동차부품",
"stock_Div_PER": "14.18",
"Current_PER": "43.52",
"Current_PER_Rank": "66",
"Close_Price": "5990",
"PER_Target_1": "2748",
"PER_Target_2": "4885",
"PER_Target_Avr": "3816",
"Price_over_PERAvg": "1.56950085156557",
"stock_Div_PBR": "0.99",
"Current_PBR": "1.51",
"Current_PBR_Rank": "122",
"PBR_Target_1": "3667",
"PBR_Target_2": "3540",
"PBR_Target_Avr": "3604",
"Price_over_PBRAvg": "",
"SRIM_1": "3773",
"SRIM_2": "3381",
"SRIM_3": "2646",
"SRIM_2R": "1.77186985092499",
"P_3": "6",
"P_2": "0",
"P_1": "-4",
"P_E": "",
"PY_3": "24",
"PY_2": "7",
"PY_1": "16",
"PY_E": "",
"MY_3": "545",
"MY_2": "653",
"MY_1": "672",
"MY_E": "",
"JY_3": "468",
"JY_2": "398",
"JY_1": "429",
"JY_E": "",
"ROE_3": "5.95",
"ROE_2": "1.03",
"ROE_1": "5.43",
"ROE_E": "",
"Total_P": "659",
"Total_Q": "10999981",
"BETA": "0.87",
"SY_R": "41.19",
"D_R": "-"
}
