{
"stock_code": "A136510",
"stock_name": "쎄미시스코",
"stock_Div": "디스플레이장비및부품",
"stock_Div_PER": "127.35",
"Current_PER": "N/A",
"Current_PER_Rank": "N/A",
"Close_Price": "8000",
"PER_Target_1": "-128241",
"PER_Target_2": "-66560",
"PER_Target_Avr": "-97400",
"Price_over_PERAvg": "-8.21351019758625E-02",
"stock_Div_PBR": "1.79",
"Current_PBR": "2.1",
"Current_PBR_Rank": "70",
"PBR_Target_1": "8759",
"PBR_Target_2": "8108",
"PBR_Target_Avr": "8434",
"Price_over_PBRAvg": "0.948597853797356",
"SRIM_1": "2036",
"SRIM_2": "623",
"SRIM_3": "29",
"SRIM_2R": "12.8346880911121",
"P_3": "-18",
"P_2": "-13",
"P_1": "-20",
"P_E": "",
"PY_3": "33",
"PY_2": "-7",
"PY_1": "-78",
"PY_E": "",
"MY_3": "250",
"MY_2": "219",
"MY_1": "171",
"MY_E": "",
"JY_3": "325",
"JY_2": "322",
"JY_1": "262",
"JY_E": "",
"ROE_3": "9.79",
"ROE_2": "2.97",
"ROE_1": "-20.51",
"ROE_E": "",
"Total_P": "451",
"Total_Q": "5472425",
"BETA": "1.16",
"SY_R": "-5.78",
"D_R": "-"
}
