{
"stock_code": "A138070",
"stock_name": "신진에스엠",
"stock_Div": "기계",
"stock_Div_PER": "N/A",
"Current_PER": "50.77",
"Current_PER_Rank": "46",
"Close_Price": "4890",
"PER_Target_1": "0",
"PER_Target_2": "7832",
"PER_Target_Avr": "3916",
"Price_over_PERAvg": "0.624361593462717",
"stock_Div_PBR": "1.5",
"Current_PBR": "0.6",
"Current_PBR_Rank": "27",
"PBR_Target_1": "11577",
"PBR_Target_2": "9424",
"PBR_Target_Avr": "10500",
"Price_over_PBRAvg": "",
"SRIM_1": "7826",
"SRIM_2": "6667",
"SRIM_3": "4652",
"SRIM_2R": "0.733408439934124",
"P_3": "6",
"P_2": "7",
"P_1": "1",
"P_E": "",
"PY_3": "55",
"PY_2": "41",
"PY_1": "30",
"PY_E": "",
"MY_3": "570",
"MY_2": "562",
"MY_1": "518",
"MY_E": "",
"JY_3": "674",
"JY_2": "695",
"JY_1": "711",
"JY_E": "",
"ROE_3": "7.74",
"ROE_2": "4.66",
"ROE_1": "3.46",
"ROE_E": "",
"Total_P": "439",
"Total_Q": "8531021",
"BETA": "0.56",
"SY_R": "14.63",
"D_R": "0.0143"
}
