{
"stock_code": "A194700",
"stock_name": "노바렉스",
"stock_Div": "제약",
"stock_Div_PER": "118.49",
"Current_PER": "14.79",
"Current_PER_Rank": "19",
"Close_Price": "41300",
"PER_Target_1": "364262",
"PER_Target_2": "42823",
"PER_Target_Avr": "203542",
"Price_over_PERAvg": "0.202906026996819",
"stock_Div_PBR": "4.27",
"Current_PBR": "2.84",
"Current_PBR_Rank": "77",
"PBR_Target_1": "64020",
"PBR_Target_2": "35825",
"PBR_Target_Avr": "49922",
"Price_over_PBRAvg": "0.827282287545696",
"SRIM_1": "25811",
"SRIM_2": "32151",
"SRIM_3": "51442",
"SRIM_2R": "1.28454910844553",
"P_3": "69",
"P_2": "74",
"P_1": "72",
"P_E": "76",
"PY_3": "113",
"PY_2": "163",
"PY_1": "270",
"PY_E": "344",
"MY_3": "1073",
"MY_2": "1591",
"MY_1": "2228",
"MY_E": "2805",
"JY_3": "789",
"JY_2": "918",
"JY_1": "1156",
"JY_E": "1421",
"ROE_3": "14.51",
"ROE_2": "17.23",
"ROE_1": "24.25",
"ROE_E": "22.61",
"Total_P": "3719",
"Total_Q": "7951108",
"BETA": "0.61",
"SY_R": "13.77",
"D_R": "0.0073"
}
