{
"stock_code": "A205500",
"stock_name": "액션스퀘어",
"stock_Div": "게임엔터테인먼트",
"stock_Div_PER": "31.4",
"Current_PER": "N/A",
"Current_PER_Rank": "N/A",
"Close_Price": "4865",
"PER_Target_1": "-1462",
"PER_Target_2": "0",
"PER_Target_Avr": "-731",
"Price_over_PERAvg": "-3.32763337893297",
"stock_Div_PBR": "4.05",
"Current_PBR": "10.93",
"Current_PBR_Rank": "34",
"PBR_Target_1": "1712",
"PBR_Target_2": "2690",
"PBR_Target_Avr": "2201",
"Price_over_PBRAvg": "2.21035892776011",
"SRIM_1": "319",
"SRIM_2": "200",
"SRIM_3": "67",
"SRIM_2R": "24.3521659029753",
"P_3": "-7",
"P_2": "-3",
"P_1": "-10",
"P_E": "",
"PY_3": "-109",
"PY_2": "-82",
"PY_1": "-19",
"PY_E": "",
"MY_3": "75",
"MY_2": "58",
"MY_1": "58",
"MY_E": "",
"JY_3": "121",
"JY_2": "202",
"JY_1": "184",
"JY_E": "",
"ROE_3": "-87.74",
"ROE_2": "-56.74",
"ROE_1": "-10.46",
"ROE_E": "",
"Total_P": "2011",
"Total_Q": "41331210",
"BETA": "0.89",
"SY_R": "-105.84",
"D_R": "-"
}
