{
"stock_code": "A205470",
"stock_name": "휴마시스",
"stock_Div": "생명과학도구및서비스",
"stock_Div_PER": "19.2",
"Current_PER": "24.31",
"Current_PER_Rank": "8",
"Close_Price": "15600",
"PER_Target_1": "11163",
"PER_Target_2": "9504",
"PER_Target_Avr": "10334",
"Price_over_PERAvg": "1.50965307011177",
"stock_Div_PBR": "5.21",
"Current_PBR": "10.96",
"Current_PBR_Rank": "26",
"PBR_Target_1": "7048",
"PBR_Target_2": "5397",
"PBR_Target_Avr": "6222",
"Price_over_PBRAvg": "2.50703093611892",
"SRIM_1": "2136",
"SRIM_2": "3376",
"SRIM_3": "8743",
"SRIM_2R": "4.62147653456552",
"P_3": "110",
"P_2": "9",
"P_1": "133",
"P_E": "",
"PY_3": "-10",
"PY_2": "-9",
"PY_1": "254",
"PY_E": "",
"MY_3": "97",
"MY_2": "92",
"MY_1": "457",
"MY_E": "",
"JY_3": "161",
"JY_2": "152",
"JY_1": "487",
"JY_E": "",
"ROE_3": "-5.38",
"ROE_2": "-7.82",
"ROE_1": "65.5",
"ROE_E": "",
"Total_P": "5339",
"Total_Q": "34194111",
"BETA": "1.57",
"SY_R": "21.02",
"D_R": "-"
}
