{
"stock_code": "A207760",
"stock_name": "미스터블루",
"stock_Div": "출판",
"stock_Div_PER": "29.06",
"Current_PER": "18.99",
"Current_PER_Rank": "2",
"Close_Price": "10600",
"PER_Target_1": "17503",
"PER_Target_2": "13902",
"PER_Target_Avr": "15702",
"Price_over_PERAvg": "0.675051743352969",
"stock_Div_PBR": "4.34",
"Current_PBR": "4.89",
"Current_PBR_Rank": "3",
"PBR_Target_1": "9788",
"PBR_Target_2": "7815",
"PBR_Target_Avr": "8802",
"Price_over_PBRAvg": "1.20434016928933",
"SRIM_1": "4196",
"SRIM_2": "6088",
"SRIM_3": "13306",
"SRIM_2R": "1.74100985658271",
"P_3": "29",
"P_2": "36",
"P_1": "74",
"P_E": "59",
"PY_3": "36",
"PY_2": "40",
"PY_1": "139",
"PY_E": "188",
"MY_3": "302",
"MY_2": "310",
"MY_1": "639",
"MY_E": "871",
"JY_3": "288",
"JY_2": "321",
"JY_1": "429",
"JY_E": "573",
"ROE_3": "10.09",
"ROE_2": "9.04",
"ROE_1": "32.13",
"ROE_E": "31.34",
"Total_P": "2625",
"Total_Q": "24217440",
"BETA": "1.22",
"SY_R": "18.88",
"D_R": "0.0024"
}
