{
"stock_code": "A208860",
"stock_name": "엔지스테크널러지",
"stock_Div": "소프트웨어",
"stock_Div_PER": "83.16",
"Current_PER": "N/A",
"Current_PER_Rank": "N/A",
"Close_Price": "4485",
"PER_Target_1": "-64466",
"PER_Target_2": "-1615884",
"PER_Target_Avr": "-840175",
"Price_over_PERAvg": "-5.3381735947868E-03",
"stock_Div_PBR": "3.78",
"Current_PBR": "5.85",
"Current_PBR_Rank": "37",
"PBR_Target_1": "3429",
"PBR_Target_2": "5668",
"PBR_Target_Avr": "4548",
"Price_over_PBRAvg": "0.986039353633066",
"SRIM_1": "413",
"SRIM_2": "137",
"SRIM_3": "8",
"SRIM_2R": "32.6278559785112",
"P_3": "37",
"P_2": "13",
"P_1": "-8",
"P_E": "",
"PY_3": "0",
"PY_2": "-9",
"PY_1": "-35",
"PY_E": "",
"MY_3": "34",
"MY_2": "42",
"MY_1": "63",
"MY_E": "",
"JY_3": "94",
"JY_2": "106",
"JY_1": "96",
"JY_E": "",
"ROE_3": "0.17",
"ROE_2": "-9.64",
"ROE_1": "-81.16",
"ROE_E": "",
"Total_P": "474",
"Total_Q": "10574379",
"BETA": "1",
"SY_R": "-13.54",
"D_R": "-"
}
