{
"stock_code": "A215480",
"stock_name": "토박스코리아",
"stock_Div": "섬유-의류-신발-호화품",
"stock_Div_PER": "32.9",
"Current_PER": "N/A",
"Current_PER_Rank": "N/A",
"Close_Price": "1270",
"PER_Target_1": "125",
"PER_Target_2": "928",
"PER_Target_Avr": "526",
"Price_over_PERAvg": "2.41215574548908",
"stock_Div_PBR": "1.34",
"Current_PBR": "2.38",
"Current_PBR_Rank": "67",
"PBR_Target_1": "714",
"PBR_Target_2": "1315",
"PBR_Target_Avr": "1014",
"Price_over_PBRAvg": "1.25184820108428",
"SRIM_1": "446",
"SRIM_2": "311",
"SRIM_3": "135",
"SRIM_2R": "4.08331879327525",
"P_3": "0",
"P_2": "",
"P_1": "",
"P_E": "",
"PY_3": "45",
"PY_2": "-24",
"PY_1": "11",
"PY_E": "",
"MY_3": "305",
"MY_2": "244",
"MY_1": "284",
"MY_E": "",
"JY_3": "206",
"JY_2": "174",
"JY_1": "227",
"JY_E": "",
"ROE_3": "3.56",
"ROE_2": "-20.42",
"ROE_1": "0.76",
"ROE_E": "",
"Total_P": "520",
"Total_Q": "41055214",
"BETA": "1.18",
"SY_R": "47.27",
"D_R": "-"
}
