{
"stock_code": "A217730",
"stock_name": "강스템바이오텍",
"stock_Div": "생물공학",
"stock_Div_PER": "N/A",
"Current_PER": "N/A",
"Current_PER_Rank": "N/A",
"Close_Price": "8750",
"PER_Target_1": "0",
"PER_Target_2": "0",
"PER_Target_Avr": "0",
"Price_over_PERAvg": "N/A",
"stock_Div_PBR": "10.99",
"Current_PBR": "3.34",
"Current_PBR_Rank": "9",
"PBR_Target_1": "30653",
"PBR_Target_2": "20000",
"PBR_Target_Avr": "25326",
"Price_over_PBRAvg": "0.345487927664699",
"SRIM_1": "989",
"SRIM_2": "232",
"SRIM_3": "5",
"SRIM_2R": "37.7398274501325",
"P_3": "-49",
"P_2": "-69",
"P_1": "-57",
"P_E": "",
"PY_3": "-117",
"PY_2": "-117",
"PY_1": "-232",
"PY_E": "",
"MY_3": "91",
"MY_2": "92",
"MY_1": "60",
"MY_E": "",
"JY_3": "235",
"JY_2": "477",
"JY_1": "707",
"JY_E": "",
"ROE_3": "-66.41",
"ROE_2": "-38.36",
"ROE_1": "-41.61",
"ROE_E": "",
"Total_P": "1836",
"Total_Q": "24219371",
"BETA": "1.27",
"SY_R": "-7.91",
"D_R": "-"
}
