{
"stock_code": "A225430",
"stock_name": "케이엠제약",
"stock_Div": "가정용품",
"stock_Div_PER": "18.57",
"Current_PER": "N/A",
"Current_PER_Rank": "N/A",
"Close_Price": "3640",
"PER_Target_1": "0",
"PER_Target_2": "0",
"PER_Target_Avr": "0",
"Price_over_PERAvg": "N/A",
"SRIM_1": "637",
"SRIM_2": "351",
"SRIM_3": "85",
"SRIM_2R": "10.3653245372007",
"P_3": "",
"P_2": "0",
"P_1": "",
"P_E": "",
"PY_3": "25",
"PY_2": "16",
"PY_1": "-15",
"PY_E": "",
"MY_3": "177",
"MY_2": "173",
"MY_1": "203",
"MY_E": "",
"JY_3": "149",
"JY_2": "238",
"JY_1": "242",
"JY_E": "255",
"ROE_3": "14.19",
"ROE_2": "-63.68",
"ROE_1": "-3.76",
"ROE_E": "",
"Total_P": "778",
"Total_Q": "21387011",
"BETA": "0.98",
"SY_R": "-51.87",
"D_R": "-"
}
