{
"stock_code": "A263770",
"stock_name": "유에스티",
"stock_Div": "철강",
"stock_Div_PER": "36.43",
"Current_PER": "42.92",
"Current_PER_Rank": "25",
"Close_Price": "5990",
"PER_Target_1": "3703",
"PER_Target_2": "7602",
"PER_Target_Avr": "5652",
"Price_over_PERAvg": "1.05970809376382",
"stock_Div_PBR": "0.59",
"Current_PBR": "2.92",
"Current_PBR_Rank": "49",
"PBR_Target_1": "1101",
"PBR_Target_2": "4500",
"PBR_Target_Avr": "2800",
"Price_over_PBRAvg": "",
"SRIM_1": "2018",
"SRIM_2": "1926",
"SRIM_3": "1739",
"SRIM_2R": "3.10934634665179",
"P_3": "0",
"P_2": "",
"P_1": "",
"P_E": "",
"PY_3": "52",
"PY_2": "34",
"PY_1": "38",
"PY_E": "",
"MY_3": "502",
"MY_2": "496",
"MY_1": "524",
"MY_E": "",
"JY_3": "355",
"JY_2": "438",
"JY_1": "464",
"JY_E": "",
"ROE_3": "12.85",
"ROE_2": "2.87",
"ROE_1": "5.64",
"ROE_E": "",
"Total_P": "1420",
"Total_Q": "23512659",
"BETA": "1.62",
"SY_R": "37.37",
"D_R": "-"
}
