{
"stock_code": "A267320",
"stock_name": "나인테크",
"stock_Div": "반도체와반도체장비",
"stock_Div_PER": "18.27",
"Current_PER": "20.01",
"Current_PER_Rank": "34",
"Close_Price": "2625",
"PER_Target_1": "0",
"PER_Target_2": "0",
"PER_Target_Avr": "0",
"Price_over_PERAvg": "N/A",
"SRIM_1": "592",
"SRIM_2": "1427",
"SRIM_3": "8144",
"SRIM_2R": "1.83960790695029",
"P_3": "",
"P_2": "0",
"P_1": "",
"P_E": "",
"PY_3": "-4",
"PY_2": "18",
"PY_1": "65",
"PY_E": "",
"MY_3": "515",
"MY_2": "500",
"MY_1": "752",
"MY_E": "",
"JY_3": "-11",
"JY_2": "20",
"JY_1": "99",
"JY_E": "",
"ROE_3": "완전잠식",
"ROE_2": "436.59",
"ROE_1": "71.24",
"ROE_E": "",
"Total_P": "975",
"Total_Q": "35864994",
"BETA": "1.1",
"SY_R": "15",
"D_R": "-"
}
