{
"stock_code": "A274090",
"stock_name": "켄코아에어로스페이스",
"stock_Div": "우주항공과국방",
"stock_Div_PER": "20.8",
"Current_PER": "N/A",
"Current_PER_Rank": "N/A",
"Close_Price": "8820",
"PER_Target_1": "-18179",
"PER_Target_2": "0",
"PER_Target_Avr": "-9090",
"Price_over_PERAvg": "-0.485175202156334",
"stock_Div_PBR": "2.05",
"Current_PBR": "2.4",
"Current_PBR_Rank": "11",
"PBR_Target_1": "7165",
"PBR_Target_2": "0",
"PBR_Target_Avr": "3582",
"Price_over_PBRAvg": "1.23098394975576",
"SRIM_1": "56",
"SRIM_2": "0",
"SRIM_3": "9483",
"SRIM_2R": "-23506.4312826993",
"P_3": "15",
"P_2": "0",
"P_1": "-11",
"P_E": "",
"PY_3": "-6",
"PY_2": "-9",
"PY_1": "10",
"PY_E": "",
"MY_3": "70",
"MY_2": "289",
"MY_1": "463",
"MY_E": "",
"JY_3": "152",
"JY_2": "-132",
"JY_1": "337",
"JY_E": "",
"ROE_3": "-10.24",
"ROE_2": "-926.72",
"ROE_1": "-73.7",
"ROE_E": "",
"Total_P": "795",
"Total_Q": "10509832",
"BETA": "1",
"SY_R": "79.5",
"D_R": "-"
}
