{
"stock_code": "A285490",
"stock_name": "노바텍",
"stock_Div": "핸드셋",
"stock_Div_PER": "N/A",
"Current_PER": "24.74",
"Current_PER_Rank": "15",
"Close_Price": "70900",
"PER_Target_1": "297252",
"PER_Target_2": "74299",
"PER_Target_Avr": "185776",
"Price_over_PERAvg": "0.381643435221544",
"stock_Div_PBR": "2.33",
"Current_PBR": "6.55",
"Current_PBR_Rank": "64",
"PBR_Target_1": "18394",
"PBR_Target_2": "25844",
"PBR_Target_Avr": "22119",
"Price_over_PBRAvg": "3.20538903205389",
"SRIM_1": "27193",
"SRIM_2": "44628",
"SRIM_3": "124400",
"SRIM_2R": "1.58867187555228",
"P_3": "8",
"P_2": "68",
"P_1": "126",
"P_E": "105",
"PY_3": "55",
"PY_2": "67",
"PY_1": "55",
"PY_E": "307",
"MY_3": "213",
"MY_2": "259",
"MY_1": "261",
"MY_E": "797",
"JY_3": "159",
"JY_2": "311",
"JY_1": "285",
"JY_E": "",
"ROE_3": "31.73",
"ROE_2": "29.21",
"ROE_1": "16.42",
"ROE_E": "77.28",
"Total_P": "3557",
"Total_Q": "5016338",
"BETA": "1.07",
"SY_R": "64.67",
"D_R": "0.0034"
}
