{
"stock_code": "A293780",
"stock_name": "압타바이오",
"stock_Div": "제약",
"stock_Div_PER": "99.35",
"Current_PER": "N/A",
"Current_PER_Rank": "N/A",
"Close_Price": "28350",
"PER_Target_1": "-59933",
"PER_Target_2": "0",
"PER_Target_Avr": "-29966",
"Price_over_PERAvg": "-0.473028214839905",
"stock_Div_PBR": "4.94",
"Current_PBR": "4.17",
"Current_PBR_Rank": "94",
"PBR_Target_1": "32415",
"PBR_Target_2": "34604",
"PBR_Target_Avr": "33510",
"Price_over_PBRAvg": "",
"SRIM_1": "6226",
"SRIM_2": "5174",
"SRIM_3": "3409",
"SRIM_2R": "5.47956928529198",
"P_3": "0",
"P_2": "",
"P_1": "",
"P_E": "",
"PY_3": "-21",
"PY_2": "-34",
"PY_1": "-72",
"PY_E": "",
"MY_3": "3",
"MY_2": "15",
"MY_1": "10",
"MY_E": "",
"JY_3": "-315",
"JY_2": "183",
"JY_1": "752",
"JY_E": "",
"ROE_3": "N/A(IFRS)",
"ROE_2": "완전잠식",
"ROE_1": "-13.48",
"ROE_E": "",
"Total_P": "3146",
"Total_Q": "11095233",
"BETA": "1.53",
"SY_R": "-43.69",
"D_R": "-"
}
