{
"stock_code": "A348350",
"stock_name": "위드텍",
"stock_Div": "전자장비와기기",
"stock_Div_PER": "39.13",
"Current_PER": "17.48",
"Current_PER_Rank": "17",
"Close_Price": "51900",
"PER_Target_1": "114011",
"PER_Target_2": "0",
"PER_Target_Avr": "57006",
"Price_over_PERAvg": "0.455219233231881",
"stock_Div_PBR": "3.25",
"Current_PBR": "4.08",
"Current_PBR_Rank": "66",
"PBR_Target_1": "54269",
"PBR_Target_2": "0",
"PBR_Target_Avr": "27134",
"Price_over_PBRAvg": "0.956347085813264",
"SRIM_1": "23700",
"SRIM_2": "27665",
"SRIM_3": "38627",
"SRIM_2R": "1.87599776674274",
"P_3": "0",
"P_2": "",
"P_1": "0",
"P_E": "",
"PY_3": "63",
"PY_2": "45",
"PY_1": "127",
"PY_E": "137",
"MY_3": "317",
"MY_2": "432",
"MY_1": "589",
"MY_E": "679",
"JY_3": "372",
"JY_2": "373",
"JY_1": "509",
"JY_E": "895",
"ROE_3": "15.77",
"ROE_2": "N/A(IFRS)",
"ROE_1": "26.34",
"ROE_E": "18.37",
"Total_P": "2643",
"Total_Q": "5091800",
"BETA": "4.53",
"SY_R": "20.81",
"D_R": "-"
}
