{
"stock_code": "A348210",
"stock_name": "넥스틴",
"stock_Div": "반도체와반도체장비",
"stock_Div_PER": "18.17",
"Current_PER": "27.9",
"Current_PER_Rank": "54",
"Close_Price": "59700",
"PER_Target_1": "43344",
"PER_Target_2": "81758",
"PER_Target_Avr": "62551",
"Price_over_PERAvg": "0.954421192307077",
"stock_Div_PBR": "2.76",
"Current_PBR": "11.5",
"Current_PBR_Rank": "112",
"PBR_Target_1": "19193",
"PBR_Target_2": "85351",
"PBR_Target_Avr": "52272",
"Price_over_PBRAvg": "1.1421028466483",
"SRIM_1": "23256",
"SRIM_2": "41001",
"SRIM_3": "131238",
"SRIM_2R": "1.45605117003336",
"P_3": "99",
"P_2": "57",
"P_1": "26",
"P_E": "68",
"PY_3": "-4",
"PY_2": "-18",
"PY_1": "181",
"PY_E": "302",
"MY_3": "129",
"MY_2": "94",
"MY_1": "494",
"MY_E": "884",
"JY_3": "33",
"JY_2": "14",
"JY_1": "459",
"JY_E": "700",
"ROE_3": "완전잠식",
"ROE_2": "-108.77",
"ROE_1": "62.17",
"ROE_E": "41.42",
"Total_P": "5709",
"Total_Q": "9563400",
"BETA": "1.23",
"SY_R": "31.54",
"D_R": "-"
}
